streamlit_component_video/__init__.py
streamlit_component_video/frontend/index.html
streamlit_component_video/frontend/main.js
streamlit_component_video/frontend/streamlit-component-lib.js
streamlit_component_video/frontend/style.css
streamlit_component_video/frontend/video-js.min.css
streamlit_component_video/frontend/video.min.js
streamlit_component_video-0.3.0.dist-info/LICENSE
streamlit_component_video-0.3.0.dist-info/METADATA
streamlit_component_video-0.3.0.dist-info/WHEEL
streamlit_component_video-0.3.0.dist-info/top_level.txt
streamlit_component_video-0.3.0.dist-info/RECORD
