Metadata-Version: 2.1
Name: streamlit-component-video
Version: 0.3.0
Summary: A new video with track
Author: Bob Lin
Author-email: bob401710@gmail.com
Requires-Python: >=3.7
License-File: LICENSE
Requires-Dist: streamlit >=1.2
Requires-Dist: jinja2
